[{"__type__":"cc.Prefab","_name":"SoulBoom","data":{"__id__":1}},{"__type__":"cc.Node","_name":"SoulBoom","_children":[{"__id__":2},{"__id__":4}],"_components":[{"__type__":"1b387RFEeFBtLu29HyXwdzD","node":{"__id__":1},"particle":{"__id__":4}},{"__type__":"62acalG/D9G3Z5rlcL6uaxx","node":{"__id__":1},"playOnLoad":true,"playSprite":{"__id__":3},"interval":0.06,"frameName":"SoulBoom","isDoneHide":true},{"__type__":"f18deHAI7xGi7diP4SPlBxg","node":{"__id__":1},"particleNode":{"__id__":4}},{"__type__":"cc.CircleCollider","node":{"__id__":1},"_radius":100}],"_prefab":{"__type__":"cc.PrefabInfo","root":{"__id__":1},"asset":{"__uuid__":"ab5xjEwrBCvpbvKaC6Q/Yq"},"fileId":"1cJ0r5lQhDtIr/iHztAKLP"},"_contentSize":{"__type__":"cc.Size","width":200,"height":200},"_trs":{"__type__":"TypedArray","ctor":"Float64Array","array":[0,0,0,0,0,0,1,1,1,1]},"_groupIndex":13,"groupIndex":13},{"__type__":"cc.Node","_name":"Sprite","_parent":{"__id__":1},"_components":[{"__id__":3}],"_prefab":{"__type__":"cc.PrefabInfo","root":{"__id__":1},"asset":{"__uuid__":"ab5xjEwrBCvpbvKaC6Q/Yq"},"fileId":"7c3djceX9GR4u41vK/RTA4"},"_trs":{"__type__":"TypedArray","ctor":"Float64Array","array":[0,0,0,0,0,0,1,1,1,1]},"_groupIndex":13,"groupIndex":13},{"__type__":"cc.Sprite","node":{"__id__":2},"_materials":[{"__uuid__":"ecpdLyjvZBwrvm+cedCcQy"}]},{"__type__":"cc.Node","_name":"Particle","_parent":{"__id__":1},"_components":[{"__type__":"e7cf6q5BwxOqb+AJZ7K4511","node":{"__id__":4},"_colorSplitTimes":[1],"_colorSplitColors":[{"__type__":"cc.Color","r":185,"g":94,"b":245,"a":175},{"__type__":"cc.Color","r":130,"g":46,"b":251,"a":175}],"_sizeSplitNum":3,"_sizeSplitTimes":[0.5,1],"_sizeSplitSizes":[{"__type__":"cc.Vec2"},{"__type__":"cc.Vec2","x":60,"y":10},{"__type__":"cc.Vec2"}],"prefab":{"__uuid__":"d486JSUD1Me62aTGcqEQG0"},"playOnLoad":true,"spriteFrame":[null],"duration":0.5,"launchIntervalTime":0.05,"life":0.75,"lifeRange":{"__type__":"cc.Vec2","y":0.25},"angleRange":{"__type__":"cc.Vec2","y":360},"speed":200}],"_prefab":{"__type__":"cc.PrefabInfo","root":{"__id__":1},"asset":{"__uuid__":"ab5xjEwrBCvpbvKaC6Q/Yq"},"fileId":"1bKIWGAi1MJILYQVZKziHR"},"_trs":{"__type__":"TypedArray","ctor":"Float64Array","array":[0,0,0,0,0,0,1,1,1,1]},"_groupIndex":13,"groupIndex":13}]