[{"__type__":"cc.Prefab","_name":"Skill40042Fire","data":{"__id__":1}},{"__type__":"cc.Node","_name":"Skill40042Fire","_children":[{"__id__":2}],"_components":[{"__type__":"62acalG/D9G3Z5rlcL6uaxx","node":{"__id__":1},"playOnLoad":true,"playSprite":{"__id__":3},"interval":0.05,"frameName":"Skill40042Fire"}],"_prefab":{"__type__":"cc.PrefabInfo","root":{"__id__":1},"asset":{"__uuid__":"edWscnY/1H+q1Egx6YPm77"},"fileId":"44a52+qe1A+48i6iNls1gX"},"_trs":{"__type__":"TypedArray","ctor":"Float64Array","array":[0,0,0,0,0,0,1,1,1,1]},"_groupIndex":7,"groupIndex":7},{"__type__":"cc.Node","_name":"Sprite","_parent":{"__id__":1},"_components":[{"__id__":3}],"_prefab":{"__type__":"cc.PrefabInfo","root":{"__id__":1},"asset":{"__uuid__":"edWscnY/1H+q1Egx6YPm77"},"fileId":"217Qt0Rl9Ft5UakLRoA4Pa"},"_contentSize":{"__type__":"cc.Size","width":400,"height":200},"_trs":{"__type__":"TypedArray","ctor":"Float64Array","array":[0,30.329,0,0,0,0,1,1,1,1]},"_groupIndex":7,"groupIndex":7},{"__type__":"cc.Sprite","node":{"__id__":2},"_materials":[{"__uuid__":"ecpdLyjvZBwrvm+cedCcQy"}]}]